odoo/addons/pos_supplierinfo_search/README.rst
odoo/addons/pos_supplierinfo_search/__init__.py
odoo/addons/pos_supplierinfo_search/__manifest__.py
odoo/addons/pos_supplierinfo_search/i18n/pos_supplierinfo_search.pot
odoo/addons/pos_supplierinfo_search/models/__init__.py
odoo/addons/pos_supplierinfo_search/models/product.py
odoo/addons/pos_supplierinfo_search/readme/CONTRIBUTORS.rst
odoo/addons/pos_supplierinfo_search/readme/DESCRIPTION.rst
odoo/addons/pos_supplierinfo_search/readme/USAGE.rst
odoo/addons/pos_supplierinfo_search/static/description/icon.png
odoo/addons/pos_supplierinfo_search/static/description/index.html
odoo/addons/pos_supplierinfo_search/static/src/js/db.js
odoo/addons/pos_supplierinfo_search/views/assets.xml
odoo12_addon_pos_supplierinfo_search-12.0.1.0.1.dist-info/METADATA
odoo12_addon_pos_supplierinfo_search-12.0.1.0.1.dist-info/WHEEL
odoo12_addon_pos_supplierinfo_search-12.0.1.0.1.dist-info/top_level.txt
odoo12_addon_pos_supplierinfo_search-12.0.1.0.1.dist-info/RECORD
